clipr/__init__.py
clipr/cli.py
clipr_yt-2.0.1.dist-info/METADATA
clipr_yt-2.0.1.dist-info/WHEEL
clipr_yt-2.0.1.dist-info/entry_points.txt
clipr_yt-2.0.1.dist-info/top_level.txt
clipr_yt-2.0.1.dist-info/RECORD
