Metadata-Version: 2.4
Name: clipr-yt
Version: 2.0.1
Summary: Grab any video. Instantly. - YouTube video downloader with CLI and web interface
Author-email: Nikshey Yadav <niksheyyadav@gmail.com>
License-Expression: MIT
Project-URL: Homepage, https://github.com/NiksheyYadav/Clipr
Project-URL: Documentation, https://github.com/NiksheyYadav/Clipr#readme
Project-URL: Repository, https://github.com/NiksheyYadav/Clipr
Project-URL: Issues, https://github.com/NiksheyYadav/Clipr/issues
Keywords: youtube,downloader,video,audio,mp3,cli,clipr
Classifier: Development Status :: 4 - Beta
Classifier: Environment :: Console
Classifier: Environment :: Web Environment
Classifier: Intended Audience :: End Users/Desktop
Classifier: Operating System :: OS Independent
Classifier: Programming Language :: Python :: 3
Classifier: Programming Language :: Python :: 3.8
Classifier: Programming Language :: Python :: 3.9
Classifier: Programming Language :: Python :: 3.10
Classifier: Programming Language :: Python :: 3.11
Classifier: Programming Language :: Python :: 3.12
Classifier: Topic :: Multimedia :: Video
Classifier: Topic :: Internet :: WWW/HTTP :: Indexing/Search
Requires-Python: >=3.8
Requires-Dist: pytubefix>=6.9.0
Requires-Dist: tqdm>=4.66.0
Provides-Extra: web
Requires-Dist: flask>=3.0.0; extra == "web"
Requires-Dist: flask-cors>=4.0.0; extra == "web"
Provides-Extra: dev
Requires-Dist: pytest>=8.0.0; extra == "dev"
